{
  "$schema": "https://ui.shadcn.com/schema/registry-item.json",
  "name": "domino-run",
  "description": "A receding row of dominoes toppling toward the camera one by one, then standing back up in a wave.",
  "dependencies": [
    "framer-motion"
  ],
  "files": [
    {
      "path": "registry/new-york/perspective/domino-run.tsx",
      "content": "/**\n * A receding row of dominoes toppling toward the camera one by one, then standing back up in a wave.\n */\n\"use client\";\n\nimport { motion } from \"framer-motion\";\n\nconst DOMINO_COUNT = 6;\nconst SPACING = 26;\n\nconst DominoRun = () => {\n  return (\n    <div style={{ perspective: 600 }}>\n      <div\n        className=\"relative size-40\"\n        style={{\n          transform: \"rotateX(6deg) rotateY(-30deg)\",\n          transformStyle: \"preserve-3d\",\n        }}\n      >\n        {Array.from({ length: DOMINO_COUNT }, (_, i) => (\n          <div\n            key={i}\n            className=\"absolute inset-0 flex items-center justify-center\"\n            style={{\n              transform: `translateZ(${-i * SPACING}px)`,\n              transformStyle: \"preserve-3d\",\n            }}\n          >\n            <motion.div\n              className=\"flex h-14 w-9 flex-col justify-between rounded-sm border border-foreground/30 bg-muted p-1.5\"\n              style={{ transformOrigin: \"bottom\" }}\n              initial={{ rotateX: 0 }}\n              animate={{ rotateX: -78 }}\n              transition={{\n                duration: 0.5,\n                ease: \"easeIn\",\n                delay: (DOMINO_COUNT - 1 - i) * 0.22,\n                repeat: Infinity,\n                repeatType: \"reverse\",\n                repeatDelay: 1.6,\n              }}\n            >\n              <div className=\"flex justify-center\">\n                <div className=\"size-1.5 rounded-full bg-foreground/50\" />\n              </div>\n              <div className=\"h-px w-full bg-foreground/25\" />\n              <div className=\"flex justify-between\">\n                <div className=\"size-1.5 rounded-full bg-foreground/50\" />\n                <div className=\"size-1.5 rounded-full bg-foreground/50\" />\n              </div>\n            </motion.div>\n          </div>\n        ))}\n      </div>\n    </div>\n  );\n};\n\nexport default DominoRun;\n",
      "type": "registry:component",
      "target": "components/pixel-perfect/domino-run.tsx"
    }
  ],
  "type": "registry:block"
}