{
  "$schema": "https://ui.shadcn.com/schema/registry-item.json",
  "name": "floating-logo-intro",
  "description": "A 3D logo that draws itself in (SVG stroke), rises with an easeOutBack overshoot and floats, over a cursor-distorted pixel-text background, with a hover ink-bleed reveal and click \"venom\" takeover shader.",
  "dependencies": [
    "@react-three/drei",
    "@react-three/fiber",
    "framer-motion",
    "three"
  ],
  "files": [
    {
      "path": "registry/new-york/three-js/floating-logo-intro.tsx",
      "content": "\"use client\";\n\n/**\n * A 3D logo that draws itself in (SVG stroke), rises with an easeOutBack overshoot and floats, over a cursor-distorted pixel-text background, with a hover ink-bleed reveal and click \"venom\" takeover shader.\n */\n\nimport { Canvas, useFrame, type ThreeEvent } from \"@react-three/fiber\";\nimport { Center, Environment, useGLTF } from \"@react-three/drei\";\nimport { AnimatePresence, motion } from \"framer-motion\";\nimport { Suspense, useEffect, useRef, useState } from \"react\";\nimport * as THREE from \"three\";\nimport type { Group } from \"three\";\n\nconst MODEL_URL = \"/model/polify.glb\";\n\nconst LOGO_PATH =\n  \"M726.5 0L840.5 66.5L633.5 389L491 389L420 497.5L110 497.5L0 431L278 0L726.5 0ZM398 84.5L182.5 416.5L302.5 416.5L372 306L514 306L655.5 84.5L398 84.5Z\";\n\nconst easeOutBack = (x: number, s = 1.70158) => {\n  const c1 = s;\n  const c3 = c1 + 1;\n  return 1 + c3 * Math.pow(x - 1, 3) + c1 * Math.pow(x - 1, 2);\n};\n\nconst INTRO_DUR = 1.3;\n\nconst Model = ({ play }: { play: boolean }) => {\n  const { scene } = useGLTF(MODEL_URL);\n  const ref = useRef<Group>(null);\n  const start = useRef<number | null>(null);\n\n  const hovered = useRef(false);\n  const mouseTarget = useRef(new THREE.Vector2(0.5, 0.5));\n  const uMouse = useRef({ value: new THREE.Vector2(0.5, 0.5) });\n  const uReveal = useRef({ value: 0 });\n  const uRadius = useRef({ value: 0.15 }); // fraction of the viewport\n  const uResolution = useRef({ value: new THREE.Vector2(1, 1) });\n  const painted = useRef(false);\n  const spreadTarget = useRef(0);\n  const uSpread = useRef({ value: 0 });\n  const uSpreadCenter = useRef({ value: new THREE.Vector2(0.5, 0.5) });\n  const uTime = useRef({ value: 0 });\n\n  useEffect(() => {\n    const mat = new THREE.MeshPhysicalMaterial({\n      color: \"#070707\",\n      metalness: 0.5,\n      roughness: 0.08,\n      clearcoat: 1,\n      clearcoatRoughness: 0.04,\n      envMapIntensity: 1.6,\n    });\n    const colA = new THREE.Color(\"#a855f7\");\n    const colB = new THREE.Color(\"#22d3ee\");\n\n    const edgeMat = new THREE.LineBasicMaterial({ color: 0xffffff });\n    const added: THREE.LineSegments[] = [];\n    scene.traverse((o) => {\n      const m = o as THREE.Mesh;\n      if (!m.isMesh) return;\n      m.material = mat;\n      const edges = new THREE.LineSegments(\n        new THREE.EdgesGeometry(m.geometry, 30),\n        edgeMat,\n      );\n      m.add(edges);\n      added.push(edges);\n    });\n\n    mat.onBeforeCompile = (shader) => {\n      shader.uniforms.uMouse = uMouse.current;\n      shader.uniforms.uReveal = uReveal.current;\n      shader.uniforms.uRadius = uRadius.current;\n      shader.uniforms.uResolution = uResolution.current;\n      shader.uniforms.uSpread = uSpread.current;\n      shader.uniforms.uSpreadCenter = uSpreadCenter.current;\n      shader.uniforms.uTime = uTime.current;\n      shader.uniforms.uColorA = { value: colA };\n      shader.uniforms.uColorB = { value: colB };\n\n      shader.fragmentShader = shader.fragmentShader\n        .replace(\n          \"#include <common>\",\n          `#include <common>\n          uniform vec2 uMouse; uniform float uReveal; uniform float uRadius;\n          uniform vec2 uResolution; uniform vec3 uColorA; uniform vec3 uColorB;\n          uniform float uSpread; uniform vec2 uSpreadCenter; uniform float uTime;\n          float gAmt; vec3 gCol;\n          float prHash(vec2 p){ p = fract(p*vec2(123.34,456.21)); p += dot(p,p+45.32); return fract(p.x*p.y); }\n          float prNoise(vec2 p){ vec2 i=floor(p),f=fract(p); vec2 u=f*f*(3.0-2.0*f);\n            return mix(mix(prHash(i),prHash(i+vec2(1.0,0.0)),u.x), mix(prHash(i+vec2(0.0,1.0)),prHash(i+vec2(1.0,1.0)),u.x), u.y); }\n          float prFbm(vec2 p){ float v=0.0,a=0.5; for(int i=0;i<4;i++){ v+=a*prNoise(p); p*=2.0; a*=0.5;} return v; }`,\n        )\n        .replace(\n          \"#include <color_fragment>\",\n          `#include <color_fragment>\n          {\n            vec2 sc = gl_FragCoord.xy / uResolution;\n            float aspect = uResolution.x / uResolution.y;\n\n            // hover ink-bleed spot following the cursor\n            float d = length(vec2((sc.x - uMouse.x) * aspect, sc.y - uMouse.y));\n            float warp = (prFbm(sc * 4.0) - 0.5) * uRadius * 2.2;\n            float spot = smoothstep(uRadius, uRadius * 0.1, d + warp) * uReveal;\n\n            // click spread — venom crawls out from the click point, animated\n            // fbm tendrils on the advancing edge\n            float dc = length(vec2((sc.x - uSpreadCenter.x) * aspect, sc.y - uSpreadCenter.y));\n            float tendril = (prFbm(sc * 5.0 + uTime * 0.25) - 0.5) * 0.55;\n            float thr = mix(0.0, 2.0, uSpread);\n            float spread = smoothstep(thr, thr - 0.16, dc + tendril);\n\n            gAmt = max(spot, spread);\n\n            // living veins: the gradient wobbles with animated noise\n            float veins = prFbm(sc * 9.0 + uTime * 0.4);\n            gCol = mix(uColorA, uColorB, clamp(sc.y + (veins - 0.5) * 0.45, 0.0, 1.0));\n            diffuseColor.rgb = mix(diffuseColor.rgb, gCol, gAmt * 0.8);\n          }`,\n        )\n        .replace(\n          \"#include <roughnessmap_fragment>\",\n          `#include <roughnessmap_fragment>\n          roughnessFactor = mix(roughnessFactor, 0.4, gAmt);`,\n        )\n        .replace(\n          \"#include <emissivemap_fragment>\",\n          `#include <emissivemap_fragment>\n          totalEmissiveRadiance += gCol * gAmt * 0.2;`,\n        );\n    };\n    mat.customProgramCacheKey = () => \"ink-bleed-screen-v1\";\n    mat.needsUpdate = true;\n\n    return () => {\n      mat.dispose();\n      edgeMat.dispose();\n      added.forEach((l) => {\n        l.geometry.dispose();\n        l.parent?.remove(l);\n      });\n    };\n  }, [scene]);\n\n  useFrame((state) => {\n    const g = ref.current;\n    if (!g) return;\n\n    const target = hovered.current ? 1 : 0;\n    uReveal.current.value += (target - uReveal.current.value) * 0.08;\n    mouseTarget.current.set(\n      state.pointer.x * 0.5 + 0.5,\n      state.pointer.y * 0.5 + 0.5,\n    );\n    uMouse.current.value.lerp(mouseTarget.current, 0.18);\n    uResolution.current.value.set(\n      state.gl.domElement.width,\n      state.gl.domElement.height,\n    );\n    uSpread.current.value +=\n      (spreadTarget.current - uSpread.current.value) * 0.05;\n    uTime.current.value = state.clock.elapsedTime;\n    const reveal = uReveal.current.value;\n\n    if (!play) {\n      g.position.y = -8;\n      g.scale.setScalar(0.7);\n      return;\n    }\n    if (start.current === null) start.current = state.clock.elapsedTime;\n    const t = state.clock.elapsedTime - start.current;\n\n    let base: number;\n    if (t < INTRO_DUR) {\n      const p = t / INTRO_DUR;\n      g.position.y = -8 * (1 - easeOutBack(p));\n      g.rotation.z = 0;\n      base = 0.7 + 0.3 * easeOutBack(p, 2.2);\n    } else {\n      const ft = t - INTRO_DUR;\n      const ramp = Math.min(ft / 1.2, 1);\n      g.position.y = Math.sin(ft * 1.6) * 0.5 * ramp;\n      g.rotation.z = Math.sin(ft * 1.1) * 0.06 * ramp;\n      base = 1;\n    }\n    g.scale.setScalar(base * (1 + 0.025 * reveal));\n  });\n\n  const onOver = (e: ThreeEvent<PointerEvent>) => {\n    e.stopPropagation();\n    hovered.current = true;\n  };\n  const onOut = () => {\n    hovered.current = false;\n  };\n  const onClick = (e: ThreeEvent<MouseEvent>) => {\n    e.stopPropagation();\n    painted.current = !painted.current;\n    spreadTarget.current = painted.current ? 1 : 0;\n    uSpreadCenter.current.value.copy(mouseTarget.current);\n  };\n\n  return (\n    <group ref={ref}>\n      <Center>\n        <primitive\n          object={scene}\n          onPointerOver={onOver}\n          onPointerOut={onOut}\n          onClick={onClick}\n        />\n      </Center>\n    </group>\n  );\n};\n\nuseGLTF.preload(MODEL_URL);\n\nconst GRID = 36; // fewer cells = bigger \"pixels\"\n\nconst DistortedPixels = () => {\n  const containerRef = useRef<HTMLDivElement>(null);\n\n  useEffect(() => {\n    const container = containerRef.current;\n    if (!container) return;\n\n    const renderer = new THREE.WebGLRenderer({ antialias: true, alpha: true });\n    renderer.setPixelRatio(Math.min(window.devicePixelRatio, 2));\n    container.appendChild(renderer.domElement);\n\n    const scene = new THREE.Scene();\n    const camera = new THREE.OrthographicCamera(-0.5, 0.5, 0.5, -0.5, -10, 10);\n    camera.position.z = 1;\n\n    const TS = 2048;\n    const tcan = document.createElement(\"canvas\");\n    tcan.width = TS;\n    tcan.height = TS;\n    const ctx = tcan.getContext(\"2d\")!;\n    const texture = new THREE.CanvasTexture(tcan);\n    texture.colorSpace = THREE.SRGBColorSpace;\n    texture.minFilter = THREE.LinearFilter;\n\n    const draw = () => {\n      ctx.clearRect(0, 0, TS, TS);\n      ctx.fillStyle = \"rgba(217,217,217,0.18)\"; // solid (filled), subtle\n\n      const c2d = ctx as CanvasRenderingContext2D & { letterSpacing: string };\n      ctx.textAlign = \"center\";\n      ctx.textBaseline = \"middle\";\n      ctx.font = \"700 100px 'Space Grotesk', sans-serif\";\n      c2d.letterSpacing = \"8px\";\n      const w100 = ctx.measureText(\"POLIFY\").width || 600;\n      const fs = ((TS * 0.8) / w100) * 100;\n      ctx.font = `700 ${fs}px 'Space Grotesk', sans-serif`;\n      c2d.letterSpacing = `${(8 / 100) * fs}px`;\n      ctx.fillText(\"POLIFY\", TS / 2, TS / 2);\n      texture.needsUpdate = true;\n    };\n    draw();\n    if (document.fonts?.ready) document.fonts.ready.then(draw);\n\n    const data = new Float32Array(GRID * GRID * 4);\n    const dataTexture = new THREE.DataTexture(\n      data,\n      GRID,\n      GRID,\n      THREE.RGBAFormat,\n      THREE.FloatType,\n    );\n    dataTexture.needsUpdate = true;\n\n    const uniforms = {\n      uTexture: { value: texture },\n      uDataTexture: { value: dataTexture },\n      resolution: { value: new THREE.Vector4(1, 1, 1, 1) },\n    };\n\n    const mesh = new THREE.Mesh(\n      new THREE.PlaneGeometry(1, 1),\n      new THREE.ShaderMaterial({\n        transparent: true,\n        uniforms,\n        vertexShader: /* glsl */ `\n          varying vec2 vUv;\n          void main() {\n            vUv = uv;\n            gl_Position = projectionMatrix * modelViewMatrix * vec4(position, 1.0);\n          }\n        `,\n        fragmentShader: /* glsl */ `\n          uniform sampler2D uTexture;\n          uniform sampler2D uDataTexture;\n          uniform vec4 resolution;\n          varying vec2 vUv;\n          void main() {\n            vec2 newUV = (vUv - 0.5) * resolution.zw + 0.5;\n            vec4 offset = texture2D(uDataTexture, vUv);\n            gl_FragColor = texture2D(uTexture, newUV - 0.01 * offset.rg);\n          }\n        `,\n      }),\n    );\n    scene.add(mesh);\n\n    const resize = () => {\n      const w = container.clientWidth;\n      const h = container.clientHeight;\n      if (!w || !h) return;\n      renderer.setSize(w, h);\n      const imgAspect = 1;\n      let a1 = 1;\n      let a2 = 1;\n      if (h / w > imgAspect) {\n        a1 = (w / h) * imgAspect;\n      } else {\n        a2 = h / w / imgAspect;\n      }\n      uniforms.resolution.value.set(w, h, a1, a2);\n    };\n    resize();\n    const ro = new ResizeObserver(resize);\n    ro.observe(container);\n\n    const mouse = { x: 0.5, y: 0.5, px: 0.5, py: 0.5, vx: 0, vy: 0 };\n    const onMove = (e: PointerEvent) => {\n      const r = renderer.domElement.getBoundingClientRect();\n      mouse.x = (e.clientX - r.left) / r.width;\n      mouse.y = (e.clientY - r.top) / r.height;\n      mouse.vx = mouse.x - mouse.px;\n      mouse.vy = mouse.y - mouse.py;\n      mouse.px = mouse.x;\n      mouse.py = mouse.y;\n    };\n    window.addEventListener(\"pointermove\", onMove);\n\n    const RELAX = 0.86;\n    const RADIUS = GRID / 6;\n    const updateGrid = () => {\n      for (let i = 0; i < GRID * GRID; i++) {\n        data[i * 4] *= RELAX;\n        data[i * 4 + 1] *= RELAX;\n      }\n      const gx = GRID * mouse.x;\n      const gy = GRID * (1 - mouse.y);\n      const r2 = RADIUS * RADIUS;\n      for (let i = 0; i < GRID; i++) {\n        for (let j = 0; j < GRID; j++) {\n          const dist = (gx - i) ** 2 + (gy - j) ** 2;\n          if (dist < r2) {\n            const idx = 4 * (i + GRID * j);\n            const power = Math.min(RADIUS / Math.sqrt(dist + 0.0001), 8);\n            data[idx] += 20 * mouse.vx * power;\n            data[idx + 1] -= 20 * mouse.vy * power;\n          }\n        }\n      }\n      mouse.vx *= 0.9;\n      mouse.vy *= 0.9;\n      dataTexture.needsUpdate = true;\n    };\n\n    let raf = 0;\n    const tick = () => {\n      raf = requestAnimationFrame(tick);\n      updateGrid();\n      renderer.render(scene, camera);\n    };\n    tick();\n\n    return () => {\n      cancelAnimationFrame(raf);\n      ro.disconnect();\n      window.removeEventListener(\"pointermove\", onMove);\n      if (renderer.domElement.parentNode === container)\n        container.removeChild(renderer.domElement);\n      mesh.geometry.dispose();\n      (mesh.material as THREE.Material).dispose();\n      texture.dispose();\n      dataTexture.dispose();\n      renderer.forceContextLoss();\n      renderer.dispose();\n    };\n  }, []);\n\n  return <div ref={containerRef} className=\"absolute inset-0 z-0\" aria-hidden />;\n};\n\nconst FloatingLogoIntro = () => {\n  const [showIntro, setShowIntro] = useState(true);\n  const [play, setPlay] = useState(false);\n\n  return (\n    <div className=\"relative h-full w-full overflow-hidden bg-neutral-900\">\n      <style>{`@import url('https://fonts.googleapis.com/css2?family=Space+Grotesk:wght@500;700&display=swap');`}</style>\n\n      <DistortedPixels />\n\n      <Canvas\n        style={{ position: \"absolute\", inset: 0, zIndex: 10 }}\n        dpr={[1, 2]}\n        camera={{ position: [12.4, -1.6, 0.6], fov: 50 }}\n      >\n        <ambientLight intensity={0.4} />\n        <directionalLight position={[5, 8, 5]} intensity={1} />\n        <Suspense fallback={null}>\n          <Environment preset=\"city\" />\n          <Model play={play} />\n        </Suspense>\n      </Canvas>\n\n      <AnimatePresence>\n        {showIntro && (\n          <motion.div\n            key=\"intro\"\n            className=\"absolute inset-0 z-20 grid place-items-center bg-neutral-900\"\n            initial={{ opacity: 1 }}\n            exit={{ opacity: 0 }}\n            transition={{ duration: 0.6, ease: \"easeInOut\" }}\n          >\n            <svg\n              width=\"240\"\n              viewBox=\"0 0 841 498\"\n              fill=\"none\"\n              xmlns=\"http://www.w3.org/2000/svg\"\n            >\n              <motion.path\n                d={LOGO_PATH}\n                fill=\"none\"\n                stroke=\"#D9D9D9\"\n                strokeWidth={6}\n                initial={{ pathLength: 0 }}\n                animate={{ pathLength: 1 }}\n                transition={{ duration: 1.2, ease: \"easeInOut\" }}\n                onAnimationComplete={() => {\n                  setPlay(true);\n                  setShowIntro(false);\n                }}\n              />\n            </svg>\n          </motion.div>\n        )}\n      </AnimatePresence>\n    </div>\n  );\n};\n\nexport default FloatingLogoIntro;\n",
      "type": "registry:component",
      "target": "components/pixel-perfect/floating-logo-intro.tsx"
    }
  ],
  "type": "registry:block"
}