{
  "$schema": "https://ui.shadcn.com/schema/registry-item.json",
  "name": "helix-spinner",
  "description": "A column of bars, each offset a few degrees on the Y axis, spinning together as a twisting 3D helix.",
  "dependencies": [
    "framer-motion"
  ],
  "files": [
    {
      "path": "registry/new-york/perspective/helix-spinner.tsx",
      "content": "/**\n * A column of bars, each offset a few degrees on the Y axis, spinning together as a twisting 3D helix.\n */\n\"use client\";\n\nimport { motion, useReducedMotion } from \"framer-motion\";\n\nconst BAR_COUNT = 16;\nconst TWIST_PER_BAR = -18;\n\nconst HelixSpinner = () => {\n  const shouldReduceMotion = useReducedMotion();\n\n  return (\n    <div style={{ perspective: 700 }}>\n      <div\n        className=\"flex flex-col items-center gap-[3px]\"\n        style={{ transformStyle: \"preserve-3d\" }}\n      >\n        {Array.from({ length: BAR_COUNT }, (_, i) => (\n          <motion.div\n            key={i}\n            className=\"h-1 w-24 rounded-full bg-foreground/60\"\n            initial={{ rotateY: i * TWIST_PER_BAR }}\n            animate={\n              shouldReduceMotion\n                ? undefined\n                : { rotateY: i * TWIST_PER_BAR + 360 }\n            }\n            transition={{ duration: 4, ease: \"linear\", repeat: Infinity }}\n          />\n        ))}\n      </div>\n    </div>\n  );\n};\n\nexport default HelixSpinner;\n",
      "type": "registry:component",
      "target": "components/pixel-perfect/helix-spinner.tsx"
    }
  ],
  "type": "registry:block"
}